[
 {
  "app": "onebag",
  "keyword": "winter travel packing list",
  "angle": "What to pack for a cold-weather trip, layering and carry-on tips"
 },
 {
  "app": "routevia",
  "keyword": "best time to visit Türkiye",
  "angle": "Season-by-season guide to visiting Türkiye"
 },
 {
  "app": "onebag",
  "keyword": "what to pack for a beach vacation",
  "angle": "Beach trip packing essentials, carry-on friendly"
 },
 {
  "app": "routevia",
  "keyword": "Cappadocia travel guide",
  "angle": "What to see and do in Cappadocia, hot-air balloons, cave hotels"
 },
 {
  "app": "onebag",
  "keyword": "business trip packing list",
  "angle": "Packing light for a short business trip, wrinkle-free clothing"
 },
 {
  "app": "routevia",
  "keyword": "things to do in Istanbul",
  "angle": "Top sights and neighbourhoods in Istanbul"
 },
 {
  "app": "onebag",
  "keyword": "packing cubes vs rolling clothes",
  "angle": "Comparison of packing methods for maximizing carry-on space"
 },
 {
  "app": "routevia",
  "keyword": "Antalya travel guide",
  "angle": "Beaches, old town and day trips around Antalya"
 },
 {
  "app": "onebag",
  "keyword": "international travel packing checklist",
  "angle": "Documents, adapters and essentials for travelling abroad"
 },
 {
  "app": "routevia",
  "keyword": "Türkiye itinerary 7 days",
  "angle": "A one-week Türkiye itinerary suggestion"
 },
 {
  "app": "onebag",
  "keyword": "how much does a carry-on weigh",
  "angle": "Typical carry-on weights and how to stay under airline limits"
 },
 {
  "app": "routevia",
  "keyword": "Pamukkale travel guide",
  "angle": "Visiting the travertines and Hierapolis"
 },
 {
  "app": "onebag",
  "keyword": "long haul flight essentials",
  "angle": "What to keep in your personal item for a long flight"
 },
 {
  "app": "routevia",
  "keyword": "Ephesus visiting guide",
  "angle": "How to visit the ancient city of Ephesus"
 },
 {
  "app": "onebag",
  "keyword": "minimalist packing tips",
  "angle": "How to pack less and travel one-bag every trip"
 },
 {
  "app": "routevia",
  "keyword": "best beaches in Türkiye",
  "angle": "Top coastal spots along the Aegean and Mediterranean"
 },
 {
  "app": "onebag",
  "keyword": "family travel packing list",
  "angle": "Packing efficiently when travelling with kids"
 },
 {
  "app": "routevia",
  "keyword": "renting a car in Türkiye",
  "angle": "Tips for a self-drive trip in Türkiye"
 },
 {
  "app": "onebag",
  "keyword": "travel toiletries rules",
  "angle": "TSA liquids rules and a carry-on toiletry kit"
 },
 {
  "app": "routevia",
  "keyword": "Türkiye travel tips for first-timers",
  "angle": "Practical advice for a first visit to Türkiye"
 },
 {
  "app": "onebag",
  "keyword": "how to pack a backpack for travel",
  "angle": "Loading a travel backpack for balance and access"
 },
 {
  "app": "routevia",
  "keyword": "Turkish food guide for travellers",
  "angle": "Must-try dishes region by region"
 },
 {
  "app": "onebag",
  "keyword": "weekend trip packing list",
  "angle": "A two-day carry-on packing list"
 },
 {
  "app": "routevia",
  "keyword": "best places to visit on the Turkish coast",
  "angle": "A coastal road trip highlights guide"
 },
 {
  "app": "onebag",
  "keyword": "carry-on size guide",
  "angle": "Standard carry-on dimensions by airline type"
 },
 {
  "app": "routevia",
  "keyword": "Bodrum travel guide",
  "angle": "Beaches, nightlife and day trips in Bodrum"
 },
 {
  "app": "onebag",
  "keyword": "personal item vs carry-on",
  "angle": "The difference and how to use both"
 },
 {
  "app": "routevia",
  "keyword": "Fethiye travel guide",
  "angle": "Oludeniz, paragliding and the coast"
 },
 {
  "app": "onebag",
  "keyword": "how to pack a suit in a carry-on",
  "angle": "Wrinkle-free suit packing methods"
 },
 {
  "app": "routevia",
  "keyword": "Izmir travel guide",
  "angle": "Things to do in and around Izmir"
 },
 {
  "app": "onebag",
  "keyword": "digital nomad packing list",
  "angle": "Long-term travel essentials and tech"
 },
 {
  "app": "routevia",
  "keyword": "Bursa travel guide",
  "angle": "Ottoman history and Uludag"
 },
 {
  "app": "onebag",
  "keyword": "hiking trip packing list",
  "angle": "Day-hike and multi-day hiking gear"
 },
 {
  "app": "routevia",
  "keyword": "best Turkish breakfast",
  "angle": "What a traditional kahvalti includes"
 },
 {
  "app": "onebag",
  "keyword": "cruise packing list",
  "angle": "What to pack for a cruise"
 },
 {
  "app": "routevia",
  "keyword": "Turkish bath hamam guide",
  "angle": "How a traditional hamam works"
 },
 {
  "app": "onebag",
  "keyword": "how to avoid checked bag fees",
  "angle": "Strategies to travel carry-on only"
 },
 {
  "app": "routevia",
  "keyword": "Mount Nemrut guide",
  "angle": "Visiting the giant statues at sunrise"
 },
 {
  "app": "onebag",
  "keyword": "travel capsule wardrobe",
  "angle": "Mix-and-match outfits for one-bag travel"
 },
 {
  "app": "routevia",
  "keyword": "Gobeklitepe guide",
  "angle": "The world's oldest temple"
 },
 {
  "app": "onebag",
  "keyword": "what not to pack in carry-on",
  "angle": "Prohibited and pointless items"
 },
 {
  "app": "routevia",
  "keyword": "Princes Islands Istanbul",
  "angle": "A day trip from Istanbul"
 },
 {
  "app": "onebag",
  "keyword": "how to fold clothes for travel",
  "angle": "Folding vs rolling for space"
 },
 {
  "app": "routevia",
  "keyword": "Bosphorus cruise guide",
  "angle": "Seeing Istanbul from the water"
 },
 {
  "app": "onebag",
  "keyword": "carry-on toiletry bag essentials",
  "angle": "TSA-friendly toiletry kit"
 },
 {
  "app": "routevia",
  "keyword": "Turkish coffee guide",
  "angle": "History and how it is served"
 },
 {
  "app": "onebag",
  "keyword": "road trip packing list",
  "angle": "Essentials for a self-drive trip"
 },
 {
  "app": "routevia",
  "keyword": "Lake Van travel guide",
  "angle": "Eastern Turkey's highlights"
 },
 {
  "app": "onebag",
  "keyword": "travelling with kids packing tips",
  "angle": "Packing light with children"
 },
 {
  "app": "routevia",
  "keyword": "best time to visit Cappadocia",
  "angle": "Season-by-season Cappadocia"
 },
 {
  "app": "onebag",
  "keyword": "winter sports packing list",
  "angle": "Ski and snowboard trip packing"
 },
 {
  "app": "routevia",
  "keyword": "Sumela Monastery guide",
  "angle": "Cliffside monastery near Trabzon"
 },
 {
  "app": "onebag",
  "keyword": "best travel accessories",
  "angle": "Useful gadgets for carry-on travel"
 },
 {
  "app": "routevia",
  "keyword": "Turkey travel budget tips",
  "angle": "Travelling Turkey affordably"
 },
 {
  "app": "onebag",
  "keyword": "how to pack shoes for travel",
  "angle": "Saving space and protecting shoes"
 },
 {
  "app": "routevia",
  "keyword": "Turkish street food guide",
  "angle": "Must-try street eats"
 }
]